mongo_lambda_backup/__init__.py
mongo_lambda_backup/handler.py
mongo_lambda_backup-0.3.0.dist-info/METADATA
mongo_lambda_backup-0.3.0.dist-info/RECORD
mongo_lambda_backup-0.3.0.dist-info/WHEEL
mongo_lambda_backup-0.3.0.dist-info/top_level.txt
