Metadata-Version: 2.1
Name: mongo-lambda-backup
Version: 0.3.0
Summary: Backup MongoDB databases using AWS Lambda functions
Home-page: https://github.com/m90/mongo-lambda-backup
Author: Frederik Ring
Author-email: frederik.ring@gmail.com
License: UNKNOWN
Platform: UNKNOWN
Classifier: Programming Language :: Python :: 3
Classifier: License :: OSI Approved :: MIT License
Classifier: Operating System :: OS Independent
Requires-Dist: boto3 (~=1.7.62)
Requires-Dist: pymongo (~=3.7.1)
